taped/__init__.py
taped/base.py
taped/display.py
taped/tools.py
taped/util.py
taped/examples/__init__.py
taped/examples/gauge_sample_rate_variation.py
taped/examples/listen_and_feedback.py
taped/examples/live_audio_pipelines.py
taped/examples/record_audio_to_files.py
taped/scrap/__init__.py
taped/scrap/audio_pokes.py
taped/scrap/live_audio.py
taped/scrap/live_audio_pipelining.py
taped-0.1.9.dist-info/LICENSE
taped-0.1.9.dist-info/METADATA
taped-0.1.9.dist-info/WHEEL
taped-0.1.9.dist-info/top_level.txt
taped-0.1.9.dist-info/RECORD
