Metadata-Version: 2.1
Name: taped
Version: 0.1.9
Summary: Python's serene audio accessor
Home-page: https://github.com/otosense/taped
License: apache-2.0
Keywords: audio,microphone,sound,stream2py
Platform: any
License-File: LICENSE
Requires-Dist: creek
Requires-Dist: i2
Requires-Dist: ipython
Requires-Dist: lined
Requires-Dist: matplotlib
Requires-Dist: PyAudio
Requires-Dist: soundfile
Requires-Dist: stream2py
Requires-Dist: audiostream2py
